archs4py
