Metadata-Version: 2.1
Name: archs4py
Version: 1.0.4
Summary: ARCHS4 Python package supporting data loading and data queries.
Home-page: https://github.com/maayanlab/archs4py
Author: Alexander Lachmann
Author-email: alexander.lachmann@mssm.edu
Classifier: Programming Language :: Python :: 3
Classifier: License :: OSI Approved :: Apache Software License
Classifier: Operating System :: OS Independent
Requires-Python: >=3.7
License-File: LICENSE
Requires-Dist: h5py
Requires-Dist: numpy
Requires-Dist: pandas
Requires-Dist: qnorm
Requires-Dist: setuptools
Requires-Dist: tqdm
Requires-Dist: wget
Requires-Dist: s3fs
Requires-Dist: biomart
Requires-Dist: xalign
